{"settings.json":"{\r\n  \"settingsSync.keybindingsPerPlatform\": false,\r\n  \"editor.defaultFormatter\": \"esbenp.prettier-vscode\",\r\n  \"vim.easymotion\": true,\r\n  \"vim.incsearch\": true,\r\n  \"vim.useSystemClipboard\": true,\r\n  \"vim.useCtrlKeys\": false,\r\n  \"vim.hlsearch\": true,\r\n  \"vim.insertModeKeyBindings\": [\r\n    {\r\n      \"before\": [\"j\", \"k\"],\r\n      \"after\": [\"<Esc>\"]\r\n    }\r\n  ],\r\n  \"vim.normalModeKeyBindingsNonRecursive\": [\r\n    {\r\n      \"before\": [\"<C-n>\"],\r\n      \"commands\": [\":nohl\"]\r\n    },\r\n    {\r\n      \"before\": [\"J\"],\r\n      \"after\": [\"5\", \"j\"]\r\n    },\r\n    {\r\n      \"before\": [\"K\"],\r\n      \"after\": [\"5\", \"k\"]\r\n    },\r\n    {\r\n      \"before\": [\"H\"],\r\n      \"after\": [\"5\", \"h\"]\r\n    },\r\n    {\r\n      \"before\": [\"L\"],\r\n      \"after\": [\"5\", \"l\"]\r\n    },\r\n    {\r\n      \"before\": [\"<leader>\", \"a\"],\r\n      \"after\": [\"0\"]\r\n    },\r\n    {\r\n      \"before\": [\"<leader>\", \"e\"],\r\n      \"after\": [\"$\"]\r\n    },\r\n    {\r\n      \"before\": [\"<leader>\", \"f\"],\r\n      \"after\": [\"<leader>\", \"<leader>\", \"f\"]\r\n    },\r\n    // debug keymap shortcut\r\n    {\r\n      \"before\": [\"<leader>\", \"d\", \"d\"],\r\n      \"commands\": [\"editor.debug.action.toggleBreakpoint\"]\r\n    },\r\n    {\r\n      \"before\": [\"<leader>\", \"d\", \"r\"],\r\n      \"commands\": [\"workbench.action.debug.start\"]\r\n    },\r\n    {\r\n      \"before\": [\"<leader>\", \"d\", \"n\"],\r\n      \"commands\": [\"workbench.action.debug.stepInto\"]\r\n    },\r\n    {\r\n      \"before\": [\"<leader>\", \"d\", \"p\"],\r\n      \"commands\": [\"workbench.action.debug.stepOut\"]\r\n    },\r\n    {\r\n      \"before\": [\"<leader>\", \"d\", \"c\"],\r\n      \"commands\": [\"workbench.action.debug.continue\"]\r\n    },\r\n    {\r\n      \"before\": [\"<leader>\", \"d\", \"s\"],\r\n      \"commands\": [\"workbench.action.debug.stop\"]\r\n    }\r\n  ],\r\n  \"vim.leader\": \"<space>\",\r\n  \"vim.handleKeys\": {\r\n    \"<C-a>\": false,\r\n    \"<C-f>\": false\r\n  },\r\n  \"files.autoSave\": \"onFocusChange\",\r\n  \"autoprefixer.formatOnSave\": true,\r\n  \"editor.fontFamily\": \"'JetbrainsMono NF', 'Fira Code', Consolas, 'Courier New', monospace\",\r\n  \"editor.fontLigatures\": true,\r\n  \"files.exclude\": {\r\n    \"**/.git\": true,\r\n    \"**/.svn\": true,\r\n    \"**/.hg\": true,\r\n    \"**/CVS\": true,\r\n    \"**/.DS_Store\": true,\r\n    \"**/Thumbs.db\": true\r\n    // \"**/node_modules\": true\r\n  },\r\n  \"workbench.iconTheme\": \"material-icon-theme\",\r\n  \"explorer.confirmDelete\": false,\r\n  \"security.workspace.trust.untrustedFiles\": \"open\",\r\n  \"prettier.jsxSingleQuote\": true,\r\n  \"editor.fontSize\": 16,\r\n  \"editor.unicodeHighlight.nonBasicASCII\": false,\r\n  \"typescript.updateImportsOnFileMove.enabled\": \"always\",\r\n  \"vim.easymotionDimColor\": \"#3197ff\",\r\n  \"[markdown]\": {\r\n    \"editor.wordWrap\": \"on\",\r\n    \"editor.quickSuggestions\": {\r\n      \"other\": true,\r\n      \"comments\": false,\r\n      \"strings\": false\r\n    },\r\n    \"editor.formatOnSave\": true\r\n  },\r\n  // \"prettier.semi\": false,\r\n  \"leetcode.endpoint\": \"leetcode-cn\",\r\n  \"material-icon-theme.folders.theme\": \"specific\",\r\n  \"window.menuBarVisibility\": \"toggle\",\r\n  \"javascript.updateImportsOnFileMove.enabled\": \"always\",\r\n  \"better-comments.tags\": [\r\n    {\r\n      \"tag\": \"!\",\r\n      \"color\": \"#FF2D00\",\r\n      \"strikethrough\": false,\r\n      \"underline\": false,\r\n      \"backgroundColor\": \"transparent\",\r\n      \"bold\": false,\r\n      \"italic\": false\r\n    },\r\n    {\r\n      \"tag\": \"?\",\r\n      \"color\": \"#3498DB\",\r\n      \"strikethrough\": false,\r\n      \"underline\": false,\r\n      \"backgroundColor\": \"transparent\",\r\n      \"bold\": false,\r\n      \"italic\": false\r\n    },\r\n    {\r\n      \"tag\": \"//\",\r\n      \"color\": \"#474747\",\r\n      \"strikethrough\": true,\r\n      \"underline\": false,\r\n      \"backgroundColor\": \"transparent\",\r\n      \"bold\": false,\r\n      \"italic\": false\r\n    },\r\n    {\r\n      \"tag\": \"todo\",\r\n      \"color\": \"#FF8C00\",\r\n      \"strikethrough\": false,\r\n      \"underline\": false,\r\n      \"backgroundColor\": \"transparent\",\r\n      \"bold\": false,\r\n      \"italic\": false\r\n    },\r\n    {\r\n      \"tag\": \"*\",\r\n      \"color\": \"#98C379\",\r\n      \"strikethrough\": false,\r\n      \"underline\": false,\r\n      \"backgroundColor\": \"transparent\",\r\n      \"bold\": false,\r\n      \"italic\": false\r\n    }\r\n  ],\r\n  \"liveServer.settings.port\": 3290,\r\n  \"workbench.activityBar.visible\": false,\r\n  \"workbench.editor.splitInGroupLayout\": \"vertical\",\r\n  \"workbench.startupEditor\": \"none\",\r\n  \"git.confirmSync\": false,\r\n  \"editor.lineNumbers\": \"relative\",\r\n  \"workbench.colorTheme\": \"Ayu Dark Bordered\"\r\n}","keybindings.json":"[\n    {\n        \"key\": \"ctrl+shift+alt+l\",\n        \"command\": \"bookmarks.listFromAllFiles\"\n    },\n    {\n        \"key\": \"ctrl+k ctrl+m\",\n        \"command\": \"editor.debug.action.toggleBreakpoint\",\n        \"when\": \"debuggersAvailable && editorTextFocus\"\n    }\n]","extensionList":[{"id":"aaron-bond.better-comments","uuid":"7a0110bb-231a-4598-aa1b-0769ea46d28b","name":"better-comments","publisher":"aaron-bond","version":"3.0.0"},{"id":"adpyke.codesnap","uuid":"8c1fc960-44b1-45e8-89b5-85f982fdaf27","name":"codesnap","publisher":"adpyke","version":"1.3.4"},{"id":"alefragnani.Bookmarks","uuid":"b689fcc8-d494-4dbf-a228-2c694a578afc","name":"Bookmarks","publisher":"alefragnani","version":"13.3.0"},{"id":"antfu.browse-lite","uuid":"61ce9ab3-f230-47ea-8cdc-2b5eb25f3ae2","name":"browse-lite","publisher":"antfu","version":"0.3.0"},{"id":"antfu.iconify","uuid":"14933acc-ee13-48c1-9320-e39310c683b1","name":"iconify","publisher":"antfu","version":"0.3.2"},{"id":"bradlc.vscode-tailwindcss","uuid":"4db62a7c-7d70-419c-96d2-6c3a4dc77ea5","name":"vscode-tailwindcss","publisher":"bradlc","version":"0.8.4"},{"id":"DavidAnson.vscode-markdownlint","uuid":"daf8b44d-8aae-4da2-80c5-1f770219f643","name":"vscode-markdownlint","publisher":"DavidAnson","version":"0.47.0"},{"id":"dbaeumer.vscode-eslint","uuid":"583b2b34-2c1e-4634-8c0b-0b82e283ea3a","name":"vscode-eslint","publisher":"dbaeumer","version":"2.2.2"},{"id":"dsznajder.es7-react-js-snippets","uuid":"19804510-b475-4dae-b0f7-6ca08fd1af0c","name":"es7-react-js-snippets","publisher":"dsznajder","version":"4.4.3"},{"id":"eamodio.gitlens","uuid":"4de763bd-505d-4978-9575-2b7696ecf94e","name":"gitlens","publisher":"eamodio","version":"12.0.6"},{"id":"EditorConfig.EditorConfig","uuid":"f60a60a6-95ba-42d4-b41c-3d24c1b89588","name":"EditorConfig","publisher":"EditorConfig","version":"0.16.4"},{"id":"esbenp.prettier-vscode","uuid":"96fa4707-6983-4489-b7c5-d5ffdfdcce90","name":"prettier-vscode","publisher":"esbenp","version":"9.5.0"},{"id":"golang.go","uuid":"d6f6cfea-4b6f-41f4-b571-6ad2ab7918da","name":"go","publisher":"golang","version":"0.33.0"},{"id":"hediet.vscode-drawio","uuid":"ea6a6046-2132-421f-a984-664909fcf0b8","name":"vscode-drawio","publisher":"hediet","version":"1.6.4"},{"id":"jeferwang.vscode-setting-export","uuid":"5fb44da2-d0b9-4343-adf0-cb3a7e110994","name":"vscode-setting-export","publisher":"jeferwang","version":"0.0.6"},{"id":"LeetCode.vscode-leetcode","uuid":"66682185-9f80-4b70-8b8c-9e492935c105","name":"vscode-leetcode","publisher":"LeetCode","version":"0.18.1"},{"id":"mhutchie.git-graph","uuid":"438221f8-1107-4ccd-a6fe-f3b7fe0856b7","name":"git-graph","publisher":"mhutchie","version":"1.30.0"},{"id":"mrmlnc.vscode-autoprefixer","uuid":"70159dd5-3ca5-4ccc-a7ae-011a662e08c2","name":"vscode-autoprefixer","publisher":"mrmlnc","version":"3.0.1"},{"id":"ms-azuretools.vscode-docker","uuid":"0479fc1c-3d67-49f9-b087-fb9069afe48f","name":"vscode-docker","publisher":"ms-azuretools","version":"1.22.0"},{"id":"MS-CEINTL.vscode-language-pack-zh-hans","uuid":"e4ee7751-6514-4731-9cdb-7580ffa9e70b","name":"vscode-language-pack-zh-hans","publisher":"MS-CEINTL","version":"1.66.3"},{"id":"ms-ossdata.vscode-postgresql","uuid":"cc4e97b3-c252-4e12-983f-ee5d2101c2cd","name":"vscode-postgresql","publisher":"ms-ossdata","version":"0.3.0"},{"id":"ms-python.python","uuid":"f1f59ae4-9318-4f3c-a9b5-81b2eaa5f8a5","name":"python","publisher":"ms-python","version":"2022.4.1"},{"id":"ms-python.vscode-pylance","uuid":"364d2426-116a-433a-a5d8-a5098dc3afbd","name":"vscode-pylance","publisher":"ms-python","version":"2022.5.1"},{"id":"ms-toolsai.jupyter","uuid":"6c2f1801-1e7f-45b2-9b5c-7782f1e076e8","name":"jupyter","publisher":"ms-toolsai","version":"2022.3.1000901801"},{"id":"ms-toolsai.jupyter-keymap","uuid":"9f6dc8db-620c-4844-b8c5-e74914f1be27","name":"jupyter-keymap","publisher":"ms-toolsai","version":"1.0.0"},{"id":"ms-toolsai.jupyter-renderers","uuid":"b15c72f8-d5fe-421a-a4f7-27ed9f6addbf","name":"jupyter-renderers","publisher":"ms-toolsai","version":"1.0.6"},{"id":"ms-vscode-remote.remote-containers","uuid":"93ce222b-5f6f-49b7-9ab1-a0463c6238df","name":"remote-containers","publisher":"ms-vscode-remote","version":"0.234.0"},{"id":"ms-vscode-remote.remote-wsl","uuid":"f0c5397b-d357-4197-99f0-cb4202f22818","name":"remote-wsl","publisher":"ms-vscode-remote","version":"0.66.3"},{"id":"PKief.material-icon-theme","uuid":"5db78037-f674-459f-a236-db622c427c5b","name":"material-icon-theme","publisher":"PKief","version":"4.17.0"},{"id":"ritwickdey.LiveServer","uuid":"b63c44fd-0457-4696-99e9-dbfdf70d77de","name":"LiveServer","publisher":"ritwickdey","version":"5.7.5"},{"id":"syler.sass-indented","uuid":"466468c3-1861-4ad1-bf3e-f9ad46545ebb","name":"sass-indented","publisher":"syler","version":"1.8.19"},{"id":"teabyii.ayu","uuid":"5178733e-4b02-4829-95c5-1ce970847c23","name":"ayu","publisher":"teabyii","version":"1.0.5"},{"id":"vscodevim.vim","uuid":"d96e79c6-8b25-4be3-8545-0e0ecefcae03","name":"vim","publisher":"vscodevim","version":"1.22.2"},{"id":"Vue.volar","uuid":"a5223b43-8621-4351-a14e-3d560f85f277","name":"volar","publisher":"Vue","version":"0.34.16"},{"id":"Vue.vscode-typescript-vue-plugin","uuid":"78d16c76-388b-44e4-8470-6790d6c3d2d1","name":"vscode-typescript-vue-plugin","publisher":"Vue","version":"0.34.16"},{"id":"Wscats.vue","uuid":"4eceadb6-2b61-4000-b920-61e047aaf426","name":"vue","publisher":"Wscats","version":"1.0.26"},{"id":"xabikos.JavaScriptSnippets","uuid":"a2cec723-5349-460d-9de9-0fd1f8d3456f","name":"JavaScriptSnippets","publisher":"xabikos","version":"1.8.0"},{"id":"yzhang.markdown-all-in-one","uuid":"98790d67-10fa-497c-9113-f6c7489207b2","name":"markdown-all-in-one","publisher":"yzhang","version":"3.4.3"}],"snippets":{}}